PwnModules.py
PwnModules-1.10.dist-info/LICENSE
PwnModules-1.10.dist-info/METADATA
PwnModules-1.10.dist-info/WHEEL
PwnModules-1.10.dist-info/top_level.txt
PwnModules-1.10.dist-info/RECORD
