Metadata-Version: 2.1
Name: PwnModules
Version: 1.10
Summary: A open-source Pwntools Extern Functions.
Home-page: 
Author: RedLeaves
Author-email: rx700@vip.qq.com
License: MIT
Classifier: Programming Language :: Python
Classifier: Programming Language :: Python :: 3
Classifier: Programming Language :: Python :: 3.5
Classifier: Programming Language :: Python :: 3.5
Classifier: Programming Language :: Python :: 3.6
Classifier: Programming Language :: Python :: 3.7
Classifier: Programming Language :: Python :: Implementation :: CPython
License-File: LICENSE
Requires-Dist: pwntools
